Workbook

Sheet Analysis
A3: Row Labels | B3: Count of Place_ID
A4: Automotive Services | B4: 55
A5: B2B & Logistics | B5: 15
A6: Financial & Professional Services | B6: 41
A7: Health & Wellness | B7: 82
A8: Hospitality & Tourism | B8: 289
A9: Other | B9: 5
A10: Public & Community Services | B10: 79
A11: Retail & Shopping | B11: 127
A12: Grand Total | B12: 693

Sheet Dict
A1: Main_Classification | B1: Macro_Sector
A2: Restaurant | B2: Hospitality & Tourism
A3: Lodging | B3: Hospitality & Tourism
A4: Bar | B4: Hospitality & Tourism
A5: Cafe | B5: Hospitality & Tourism
A6: Night Club | B6: Hospitality & Tourism
A7: Casino | B7: Hospitality & Tourism
A8: Travel Agency | B8: Hospitality & Tourism
A9: Tourist Attraction | B9: Hospitality & Tourism
A10: Store | B10: Retail & Shopping
A11: Supermarket | B11: Retail & Shopping
A12: Grocery Or Supermarket | B12: Retail & Shopping
... A59: Food | B59: Retail & Shopping

Sheet Datos_from_API
A1: Place_ID | B1: Business_Name | C1: Target_Industry | D1: Main_Classification | E1: Macro_Sector | F1: Sub_Categories | G1: Price_Level_(0-4) | H1: Average_Rating | I1: Total_Reviews | J1: Address | K1: Latitude | L1: Longitude
A2: ChIJDfY6Avd_r44REWqUIsQAJQs | B2: Impuestos Internos | C2: Accounting | D2: Local Government Office | E2: =VLOOKUP(D2,Dict!A:B,2,FALSE) -> Public & Community Services | F2: Accounting, Finance, Point Of Interest, Establishment | G2: Not available | H2: 4.9 | I2: 8 | J2: Plaza Villa Florencia, Avenue 20 de Diciembre, local 102, Boca Chica | K2: 18.449174 | L2: -69.606467
A3: ChIJNwzJ-zh-r44RzNLvYgaJjPg | B3: MELC Solucines Agiles | C3: Accounting | D3: Accounting | E3: =VLOOKUP(D3,Dict!A:B,2,FALSE) -> Financial & Professional Services | F3: Finance, Point Of Interest, Establishment | G3: Not available | H3: 0 | I3: 0 | J3: Avenue Duarte 28, Boca Chica | K3: 18.447673 | L3: -69.606161
A4: ChIJtQyC_kZ-r44R6hx4hFhBgMQ | B4: Cajero Automatico Banco BHD | C4: Atm | D4: Atm | E4: =VLOOKUP(D4,Dict!A:B,2,FALSE) -> Financial & Professional Services | F4: Finance, Point Of Interest, Establishment | G4: Not available | H4: 3 | I4: 3 | J4: F93V+6GM, Boca Chica | K4: 18.453098 | L4: -69.60619
A5: ChIJG62zgzd-r44RBZ1MYpzssIk | B5: Bank Machine | C5: Atm | D5: Atm | E5: =VLOOKUP(D5,Dict!A:B,2,FALSE) -> Financial & Professional Services | F5: Finance, Point Of Interest, Establishment | G5: Not available | H5: 4.7 | I5: 3 | J5: C9XQ+5X9, Avenue Duarte, Boca Chica | K5: 18.447911 | L5: -69.61003
A6: ChIJS3AOhK5_r44Rv-hU7JC2oL8 | B6: ATM Cajero Triinet Whala! Boca Chica | C6: Atm | D6: Atm | E6: =VLOOKUP(D6,Dict!A:B,2,FALSE) -> Financial & Professional Services | F6: Finance, Point Of Interest, Establishment | G6: Not available | H6: 4.7 | I6: 3 | J6: C9WQ+RR Whala!, Boca Chica | K6: 18.447058 | L6: -69.610408
A7: ChIJCfNRFsx_r44RWyP09F-A3ug | B7: Cajero Automático Banco Popular | C7: Atm | D7: Atm | E7: =VLOOKUP(D7,Dict!A:B,2,FALSE) -> Financial & Professional Services | F7: Finance, Point Of Interest, Establishment | G7: Not available | H7: 5 | I7: 2 | J7: Calle San Andres 6, Andrés | K7: 18.445365 | L7: -69.626432
A8: ChIJS8-NI15_r44RZbxvvMU6vvU | B8: ATM Cajero Triinet Costa Linda | C8: Atm | D8: Atm | E8: =VLOOKUP(D8,Dict!A:B,2,FALSE) -> Financial & Professional Services | F8: Finance, Point Of Interest, Establishment | G8: Not available | H8: 3 | I8: 2 | J8: Hotel Costa Linda, Abraham Nunez 1, Boca Chica | K8: 18.447316 | L8: -69.608432
A9: ChIJ77Jec8F_r44R0FwRziQj-Cg | B9: Cajero automático Banco Popular | C9: Atm | D9: Atm | E9: =VLOOKUP(D9,Dict!A:B,2,FALSE) -> Financial & Professional Services | F9: Finance, Point Of Interest, Establishment | G9: Not available | H9: 5 | I9: 1 | J9: Avenue Duarte esq, Boca Chica | K9: 18.4479 | L9: -69.609842
A10: ChIJqbg4yyN_r44R7bLPPj8W3ic | B10: ATM Cajero Triinet Home Liquor | C10: Atm | D10: Atm | E10: =VLOOKUP(D10,Dict!A:B,2,FALSE) -> Financial & Professional Services | F10: Finance, Point Of Interest, Establishment | G10: Not available | H10: 4 | I10: 1 | J10: Home Liquor, Autopista Las Américas, Boca Chica | K10: 18.451082 | L10: -69.627901
A11: ChIJpa1HoWN_r44RP9tMWmELU4M | B11: ATM Cajero Triinet Boca Beach | C11: Atm | D11: Atm | E11: =VLOOKUP(D11,Dict!A:B,2,FALSE) -> Financial & Professional Services | F11: Finance, Point Of Interest, Establishment | G11: Not available | H11: 0 | I11: 0 | J11: Boca Beach Residence Hotel, Avenida Abraham Núñez, Boca Chica | K11: 18.447656 | L11: -69.613817
A12: ChIJq2dXVip_r44RvOgpAt0RzOM | B12: Cajero automático Banco Popular | C12: Atm | D12: Atm | E12: =VLOOKUP(D12,Dict!A:B,2,FALSE) -> Financial & Professional Services | F12: Finance, Point Of Interest, Establishment | G12: Not available | H12: 0 | I12: 0 | J12: Calle Andres Boca Chica No.16, Andres Boca Chica C/ Andres Boca Chica No.16, Boca Chica | K12: 18.445016 | L12: -69.627799
A13: ChIJ2Q1Dxbt_r44R4ytdQQmImv4 | B13: D'Jazmin Cake | C13: Bakery | D13: Bakery | E13: =VLOOKUP(D13,Dict!A:B,2,FALSE) -> Retail & Shopping | F13: Store, Point Of Interest, Food, Establishment | G13: Not available | H13: 4.3 | I13: 8 | J13: C9WF+VCJ, Calle Mella, Boca Chica | K13: 18.447203 | L13: -69.626474
... A24: ChIJ0yy1aTZ-r44RgNBlihJKMUU | B24: Banca solidaria boca chica | C24: Bank | D24: Bank | E24: =VLOOKUP(D24,Dict!A:B,2,FALSE) -> Financial & Professional Services | F24: Finance, Point Of Interest, Establishment | G24: Not available | H24: 0 | I24: 0 | J24: Avenue 20 de Diciembre 10, Boca Chica | K24: 18.449005 | L24: -69.614093
A25: ChIJLwbAbzd-r44RCIL21oErICM | B25: Mie by Sporting Club Boca Chica | C25: Bar | D25: Restaurant | E25: =VLOOKUP(D25,Dict!A:B,2,FALSE) -> Hospitality & Tourism | F25: Bar, Point Of Interest, Food, Establishment | G25: 2 | H25: 4.3 | I25: 1246 | J25: Avenida Abraham Núñez, Boca Chica | K25: 18.447381 | L25: -69.611148
A26: ChIJWXL8zzl-r44Rdhxy34frmtQ | B26: Mamajuana beach | C26: Bar | D26: Bar | E26: =VLOOKUP(D26,Dict!A:B,2,FALSE) -> Hospitality & Tourism | F26: Restaurant, Point Of Interest, Food, Establishment | G26: 2 | H26: 3 | I26: 166 | J26: Abraham Nunez 6, Boca Chica | K26: 18.446945 | L26: -69.608817
A27: ChIJ9Rhw8ct_r44RxD56E9dws70 | B27: FIRE DISCOTEC | C27: Bar | D27: Bar | E27: =VLOOKUP(D27,Dict!A:B,2,FALSE) -> Hospitality & Tourism | F27: Point Of Interest, Establishment | G27: 2 | H27: 4 | I27: 112 | J27: Calle Mella 4, Andrés | K27: 18.447189 | L27: -69.626487
A28: ChIJVa8DNTh-r44Rp7frHidP-PQ | B28: Tentacion Lounge Bar | C28: Bar | D28: Bar | E28: =VLOOKUP(D28,Dict!A:B,2,FALSE) -> Hospitality & Tourism | F28: Restaurant, Point Of Interest, Food, Establishment | G28: 2 | H28: 4.2 | I28: 77 | J28: ave. Duarte 25, Boca Chica, Boca Chica | K28: 18.447917 | L28: -69.608969
A29: ChIJ1aIDQyd_r44RFk4kBaYSOOs | B29: Piano Bar | C29: Bar | D29: Bar | E29: =VLOOKUP(D29,Dict!A:B,2,FALSE) -> Hospitality & Tourism | F29: Point Of Interest, Establishment | G29: 2 | H29: 3.9 | I29: 38 | J29: Avenue Duarte, Boca Chica | K29: 18.447867 | L29: -69.608746
A30: ChIJu8cpzNd_r44RvdKuudIezVs | B30: Amigos Night Life Boca Chica | C30: Bar | D30: Bar | E30: =VLOOKUP(D30,Dict!A:B,2,FALSE) -> Hospitality & Tourism | F30: Health, Point Of Interest, Establishment | G30: Not available | H30: 4 | I30: 34 | J30: Abraham Nunez 30, Boca Chica | K30: 18.447959 | L30: -69.612835
A31: ChIJlzS4nu9_r44RUBEIQu0QH1I | B31: Restaurante la oveja manza beach | C31: Bar | D31: Bar | E31: =VLOOKUP(D31,Dict!A:B,2,FALSE) -> Hospitality & Tourism | F31: Point Of Interest, Establishment | G31: Not available | H31: 4.5 | I31: 26 | J31: C9XM+4QM, Boca Chica | K31: 18.448125 | L31: -69.615371
A32: ChIJD7Y1tYt_r44RuP8GpMgQS6o | B32: Agiz Lounge • Restaurant | C32: Bar | D32: Bar | E32: =VLOOKUP(D32,Dict!A:B,2,FALSE) -> Hospitality & Tourism | F32: Point Of Interest, Establishment | G32: Not available | H32: 4 | I32: 24 | J32: C9WF+GP4, Andrés | K32: 18.446227 | L32: -69.625667
A33: ChIJ-SaFRXp_r44RdNG3X86qK8M | B33: Madre Lunch Bar | C33: Bar | D33: Bar | E33: =VLOOKUP(D33,Dict!A:B,2,FALSE) -> Hospitality & Tourism | F33: Point Of Interest, Establishment | G33: Not available | H33: 4.2 | I33: 21 | J33: Calle Mella 12, Andrés | K33: 18.447449 | L33: -69.626608
A34: ChIJvR-IKhSJr44Rtqjwm8OtwS4 | B34: Boca chicas | C34: Bar | D34: Bar | E34: =VLOOKUP(D34,Dict!A:B,2,FALSE) -> Hospitality & Tourism | F34: Point Of Interest, Establishment | G34: Not available | H34: 4.2 | I34: 17 | J34: F92R+6JM, Santo Domingo | K34: 18.450581 | L34: -69.608457
A35: ChIJz4u8k2N_r44R5SBVD2t3VPs | B35: LA EMBAJADA SOCIAL CLUB | C35: Bar | D35: Bar | E35: =VLOOKUP(D35,Dict!A:B,2,FALSE) -> Hospitality & Tourism | F35: Point Of Interest, Establishment | G35: Not available | H35: 4 | I35: 13 | J35: F98V+R85, Boca Chica | K35: 18.467 | L35: -69.606636
A36: ChIJjfLnjjt_r44RoEf0MvQhCDw | B36: La Cantina | C36: Bar | D36: Bar | E36: =VLOOKUP(D36,Dict!A:B,2,FALSE) -> Hospitality & Tourism | F36: Point Of Interest, Establishment | G36: Not available | H36: 4.8 | I36: 13 | J36: Calle San Andres 5, Andrés | K36: 18.447153 | L36: -69.626472
A37: ChIJyxeKmjh-r44R1ACbiOqLi68 | B37: Bodegas Max | C37: Bar | D37: Bar | E37: =VLOOKUP(D37,Dict!A:B,2,FALSE) -> Hospitality & Tourism | F37: Point Of Interest, Establishment | G37: Not available | H37: 4.1 | I37: 12 | J37: C9XV+RMC, Calle José Francisco Peña Goméz, Boca Chica | K37: 18.449574 | L37: -69.605861
A38: ChIJv3RBLTh-r44RMHcHJmKYZkk | B38: Dapathan | C38: Bar | D38: Bar | E38: =VLOOKUP(D38,Dict!A:B,2,FALSE) -> Hospitality & Tourism | F38: Point Of Interest, Establishment | G38: 2 | H38: 3.8 | I38: 12 | J38: Avenue Duarte 35, Boca Chica | K38: 18.44761 | L38: -69.608847
A39: ChIJa9KLTeB_r44RYRqn7dr7uSI | B39: Bryan Hookah Vape Store | C39: Bar | D39: Bar | E39: =VLOOKUP(D39,Dict!A:B,2,FALSE) -> Hospitality & Tourism | F39: Point Of Interest, Establishment | G39: Not available | H39: 3.6 | I39: 10 | J39: Prolongación caracol Calle Rafael Colon, Santo Domingo Este | K39: 18.459677 | L39: -69.605229
A40: ChIJS9hAQ9N_r44RnQj9G5vWa50 | B40: Billar Geymar | C40: Bar | D40: Bar | E40: =VLOOKUP(D40,Dict!A:B,2,FALSE) -> Hospitality & Tourism | F40: Point Of Interest, Establishment | G40: Not available | H40: 4 | I40: 10 | J40: F92P+GV, Juan Alberto Ozoria, Boca Chica | K40: 18.451348 | L40: -69.612893
A41: ChIJD_WXWMh_r44RSBeUIJfUCkQ | B41: Caffetteria da Michele | C41: Bar | D41: Bar | E41: =VLOOKUP(D41,Dict!A:B,2,FALSE) -> Hospitality & Tourism | F41: Point Of Interest, Establishment | G41: 1 | H41: 4.9 | I41: 8 | J41: Avenue Duarte 46, Boca Chica | K41: 18.447564 | L41: -69.607629
A42: ChIJZVNLUT9-r44R7O3rxN5HHiU | B42: Bejuko Bar | C42: Bar | D42: Bar | E42: =VLOOKUP(D42,Dict!A:B,2,FALSE) -> Hospitality & Tourism | F42: Point Of Interest, Establishment | G42: Not available | H42: 4.1 | I42: 7 | J42: C9XW+QP5, Calle Duarte, Boca Chica | K42: 18.449379 | L42: -69.603138
A43: ChIJh7kGkkR_r44RWOuUr0KxPJg | B43: Colmado disco bar | C43: Bar | D43: Bar | E43: =VLOOKUP(D43,Dict!A:B,2,FALSE) -> Hospitality & Tourism | F43: Point Of Interest, Establishment | G43: Not available | H43: 4.1 | I43: 7 | J43: F92V+7JM, Calle José Francisco Peña Goméz, Boca Chica | K43: 18.450713 | L43: -69.605966
A44: ChIJ6dK9yDh-r44RDjja1EVtTs0 | B44: Mr. Roger Bar | C44: Bar | D44: Bar | E44: =VLOOKUP(D44,Dict!A:B,2,FALSE) -> Hospitality & Tourism | F44: Point Of Interest, Establishment | G44: Not available | H44: 4.8 | I44: 5 | J44: Calle Duarte 26, Boca Chica | K44: 18.448229 | L44: -69.604252
A45: ChIJNzmrsZp_r44RjG_4rMjfAjw | B45: Pussycat Bar & Lounge | C45: Bar | D45: Bar | E45: =VLOOKUP(D45,Dict!A:B,2,FALSE) -> Hospitality & Tourism | F45: Point Of Interest, Establishment | G45: Not available | H45: 5 | I45: 5 | J45: Calle Duarte 21, Boca Chica | K45: 18.44932 | L45: -69.605312
A46: ChIJ-Tnx-eB_r44RuxqRRd43OT8 | B46: Puffy Drinks | C46: Bar | D46: Bar | E46: =VLOOKUP(D46,Dict!A:B,2,FALSE) -> Hospitality & Tourism | F46: Point Of Interest, Establishment | G46: Not available | H46: 5 | I46: 5 | J46: prolongacion caracol, Boca Chica | K46: 18.460566 | L46: -69.605365
A47: ChIJwYrGyGx_r44RFE3ds4Fcam0 | B47: Colmado music | C47: Bar | D47: Bar | E47: =VLOOKUP(D47,Dict!A:B,2,FALSE) -> Hospitality & Tourism | F47: Point Of Interest, Establishment | G47: Not available | H47: 4.5 | I47: 4 | J47: C9XR+4MC, Avenue Duarte, Boca Chica | K47: 18.4478 | L47: -69.608367
A48: ChIJCx5PI39_r44R0_ErzCAIQwk | B48: ISCAH ENTERPRISE INC | C48: Bar | D48: Car Wash | E48: =VLOOKUP(D48,Dict!A:B,2,FALSE) -> Automotive Services | F48: Beauty Salon, Bar, Point Of Interest, Establishment | G48: Not available | H48: 5 | I48: 4 | J48: Luis Leyba 39, Boca Chica | K48: 18.462381 | L48: -69.600579
A49: ChIJXW0ow0R_r44Rg5vcgB7jM9Q | B49: Manantial | C49: Bar | D49: Bar | E49: =VLOOKUP(D49,Dict!A:B,2,FALSE) -> Hospitality & Tourism | F49: Point Of Interest, Establishment | G49: Not available | H49: 3.5 | I49: 4 | J49: C9XJ+5G4, Calle Bahía San Andres, Boca Chica | K49: 18.447891 | L49: -69.618683
A50: ChIJ3wCmKgB_r44RoZHZyJuM_Bc | B50: YuYu Restaurant | C50: Bar | D50: Restaurant | E50: =VLOOKUP(D50,Dict!A:B,2,FALSE) -> Hospitality & Tourism | F50: Night Club, Bar, Point Of Interest, Food, Establishment | G50: Not available | H50: 5 | I50: 3 | J50: 18.447556,-69.607391, Avenue Duarte 24, Boca Chica | K50: 18.44763 | L50: -69.606988
A51: ChIJeVQ0Mjh-r44RVCHpiuoUqfc | B51: Full Drink | C51: Bar | D51: Bar | E51: =VLOOKUP(D51,Dict!A:B,2,FALSE) -> Hospitality & Tourism | F51: Point Of Interest, Establishment | G51: Not available | H51: 4 | I51: 3 | J51: C9XR+4HW, Boca Chica | K51: 18.447871 | L51: -69.608537
A52: ChIJFRxey3N_r44RmhF0zoWy24g | B52: Adler Bar | C52: Bar | D52: Bar | E52: =VLOOKUP(D52,Dict!A:B,2,FALSE) -> Hospitality & Tourism | F52: Point Of Interest, Establishment | G52: Not available | H52: 5 | I52: 3 | J52: Avenue San Rafael 91, Boca Chica | K52: 18.448335 | L52: -69.61213
A53: ChIJWxQ7dIN_r44RqcRBSokB5ps | B53: Pescaderia el sazon de dona Felicia | C53: Bar | D53: Bar | E53: =VLOOKUP(D53,Dict!A:B,2,FALSE) -> Hospitality & Tourism | F53: Point Of Interest, Establishment | G53: Not available | H53: 5 | I53: 3 | J53: C9XP+69C, Boca Chica | K53: 18.448029 | L53: -69.614183
... A443: ChIJ301iYT9-r44RtkToC6g6a48 | B443: DulceVilla_en la playa | C443: Lodging | D443: Lodging | E443: =VLOOKUP(D443,Dict!A:B,2,FALSE) -> Hospitality & Tourism | F443: Point Of Interest, Establishment | G443: Not available | H443: 0 | I443: 0 | J443: Dominican Republic | K443: 18.449333 | L443: -69.60173
A444: ChIJreJ0Vjh-r44RjMaPbjkTgWY | B444: Hotel hamaca | C444: Night_Club | D444: Night Club | E444: =VLOOKUP(D444,Dict!A:B,2,FALSE) -> Hospitality & Tourism | F444: Point Of Interest, Establishment | G444: 1 | H444: 4.2 | I444: 27 | J444: C9XV+34Q, Boca Chica | K444: 18.447705 | L444: -69.607143
A445: ChIJBXvwl09-r44RKYIrdIJtZMg | B445: M&E DISCOTECA | C445: Night_Club | D445: Night Club | E445: =VLOOKUP(D445,Dict!A:B,2,FALSE) -> Hospitality & Tourism | F445: Point Of Interest, Establishment | G445: Not available | H445: 3.8 | I445: 13 | J445: Calle Hilda Gutierrez 3, Boca Chica | K445: 18.460273 | L445: -69.610945
A446: ChIJswLC1TJ_r44RalJf3oqArA8 | B446: La Paloma Disco | C446: Night_Club | D446: Night Club | E446: =VLOOKUP(D446,Dict!A:B,2,FALSE) -> Hospitality & Tourism | F446: Point Of Interest, Establishment | G446: 1 | H446: 3.8 | I446: 13 | J446: alcider75@gmail.com yeremijavierruben@gmail.com, Boca Chica | K446: 18.466173 | L446: -69.609983
A447: ChIJsRpmdoF_r44R8KBe88jsHlA | B447: Alpachino | C447: Night_Club | D447: Night Club | E447: =VLOOKUP(D447,Dict!A:B,2,FALSE) -> Hospitality & Tourism | F447: Point Of Interest, Establishment | G447: Not available | H447: 4.5 | I447: 6 | J447: Calle Mella 20, Boca Chica | K447: 18.447835 | L447: -69.62657
A448: ChIJt4xTGkd-r44RSnsX4D36w5o | B448: Bar Green Playboy | C448: Night_Club | D448: Night Club | E448: =VLOOKUP(D448,Dict!A:B,2,FALSE) -> Hospitality & Tourism | F448: Point Of Interest, Establishment | G448: Not available | H448: 4.5 | I448: 4 | J448: F92V+WJG, Boca Chica | K448: 18.452304 | L448: -69.605918
A449: ChIJ8Yyb-EB_r44Rwz1-NAg29kE | B449: LA 70 Drink | C449: Night_Club | D449: Night Club | E449: =VLOOKUP(D449,Dict!A:B,2,FALSE) -> Hospitality & Tourism | F449: Point Of Interest, Establishment | G449: Not available | H449: 4 | I449: 2 | J449: Tatica Castro 12, Boca Chica | K449: 18.45119 | L449: -69.612712
A450: ChIJ9xcFUAB_r44RqxLa3gr_g0s | B450: Taxi boca chica | C450: Night_Club | D450: Night Club | E450: =VLOOKUP(D450,Dict!A:B,2,FALSE) -> Hospitality & Tourism | F450: Point Of Interest, Establishment | G450: Not available | H450: 5 | I450: 1 | J450: Calle José Francisco Peña Goméz 40, Boca Chica | K450: 18.453695 | L450: -69.605473
A451: ChIJd2l4CwB_r44RSyesh5AJriY | B451: El Último trago | C451: Night_Club | D451: Night Club | E451: =VLOOKUP(D451,Dict!A:B,2,FALSE) -> Hospitality & Tourism | F451: Point Of Interest, Establishment | G451: Not available | H451: 5 | I451: 1 | J451: F96R+5XW, Rafael Colon, Boca Chica | K451: 18.460499 | L451: -69.607535
A452: ChIJy4BoSQB_r44RiqMaeChaeSI | B452: Kotice Discotec | C452: Night_Club | D452: Night Club | E452: =VLOOKUP(D452,Dict!A:B,2,FALSE) -> Hospitality & Tourism | F452: Point Of Interest, Establishment | G452: Not available | H452: 0 | I452: 0 | J452: Avenue 20 de Diciembre 17, Boca Chica | K452: 18.449338 | L452: -69.605112
A453: ChIJoaH4ZQB_r44RuknrphwEIx4 | B453: Mamey de guerra | C453: Night_Club | D453: Night Club | E453: =VLOOKUP(D453,Dict!A:B,2,FALSE) -> Hospitality & Tourism | F453: Point Of Interest, Establishment | G453: Not available | H453: 0 | I453: 0 | J453: C9XV+QP4, Boca Chica | K453: 18.449389 | L453: -69.605661
A454: ChIJRbjyYAB_r44RStwIOJcgBfk | B454: Ballaguana | C454: Night_Club | D454: Night Club | E454: =VLOOKUP(D454,Dict!A:B,2,FALSE) -> Hospitality & Tourism | F454: Point Of Interest, Establishment | G454: Not available | H454: 0 | I454: 0 | J454: C9XV+QP4, Boca Chica | K454: 18.449389 | L454: -69.605661
A455: ChIJcy6kiv1_r44RnQJvOl0dvHA | B455: Los Morenos Sport Bar & Discotec | C455: Night_Club | D455: Night Club | E455: =VLOOKUP(D455,Dict!A:B,2,FALSE) -> Hospitality & Tourism | F455: Point Of Interest, Establishment | G455: Not available | H455: 0 | I455: 0 | J455: F95W+R6H, Rafael Colon, Boca Chica | K455: 18.459563 | L455: -69.604386
A456: ChIJJ_fDBlN_r44RuNZFdHIibks | B456: Oro20Up | C456: Night_Club | D456: Night Club | E456: =VLOOKUP(D456,Dict!A:B,2,FALSE) -> Hospitality & Tourism | F456: Point Of Interest, Establishment | G456: Not available | H456: 0 | I456: 0 | J456: C9XP+JH2, Avenue 20 de Diciembre, Boca Chica | K456: 18.449004 | L456: -69.613613
A457: ChIJtcyS7ct_r44Rj_7h8FvmlaE | B457: MELLA Park | C457: Park | D457: Park | E457: =VLOOKUP(D457,Dict!A:B,2,FALSE) -> Public & Community Services | F457: Point Of Interest, Establishment | G457: Not available | H457: 4.2 | I457: 51 | J457: C9WF+XG7, Boca Chica | K457: 18.447401 | L457: -69.626204
A458: ChIJ1WY4t-p_r44Rv3F8lgTedOU | B458: Municipal De Boca Chica Park | C458: Park | D458: Park | E458: =VLOOKUP(D458,Dict!A:B,2,FALSE) -> Public & Community Services | F458: Point Of Interest, Establishment | G458: Not available | H458: 4.7 | I458: 7 | J458: C9XR+748, Boca Chica | K458: 18.448157 | L458: -69.609661
... A496: ChIJj1PJ3tZ_r44RHTq1LKtxWF4 | B496: Urban Home | C496: Real_Estate_Agency | D496: Real Estate Agency | E496: =VLOOKUP(D496,Dict!A:B,2,FALSE) -> Financial & Professional Services | F496: Point Of Interest, Establishment | G496: Not available | H496: 0 | I496: 0 | J496: C/ Los Rieles, #21, Los tanquesitos, Andrés, Municipio Boca Chica, Santo Domimgo | K496: 18.452686 | L496: -69.627693
A497: ChIJI7fG_TZ-r44RFFWaz-QbWbc | B497: Bocana Beach & Club | C497: Restaurant | D497: Restaurant | E497: =VLOOKUP(D497,Dict!A:B,2,FALSE) -> Hospitality & Tourism | F497: Food, Point Of Interest, Establishment | G497: 2 | H497: 4.3 | I497: 8298 | J497: Abraham Nunez 27, Boca Chica | K497: 18.447431 | L497: -69.612584
A498: ChIJsRe6eDV-r44Ro8hwbzhFkd8 | B498: Boca Marina | C498: Restaurant | D498: Restaurant | E498: =VLOOKUP(D498,Dict!A:B,2,FALSE) -> Hospitality & Tourism | F498: Food, Point Of Interest, Establishment | G498: 3 | H498: 4.4 | I498: 4030 | J498: Calle Duarte 12-A, Boca Chica | K498: 18.447931 | L498: -69.601665
A499: ChIJAwQASj9-r44R6S797j8dziY | B499: Neptuno's Club Restaurant | C499: Restaurant | D499: Restaurant | E499: =VLOOKUP(D499,Dict!A:B,2,FALSE) -> Hospitality & Tourism | F499: Food, Point Of Interest, Establishment | G499: 3 | H499: 4.2 | I499: 2976 | J499: Calle Duarte # 05, Boca Chica Santo Domingo Este, Boca Chica | K499: 18.448181 | L499: -69.603028
A500: ChIJ3-CJNz9-r44RFs71A2LJ87I | B500: St. Tropez Restaurant | C500: Restaurant | D500: Restaurant | E500: =VLOOKUP(D500,Dict!A:B,2,FALSE) -> Hospitality & Tourism | F500: Food, Point Of Interest, Establishment | G500: 3 | H500: 4.2 | I500: 1866 | J500: Calle Duarte 27, Boca Chica | K500: 18.448336 | L500: -69.602797
A501: ChIJWTCqyzh-r44Rc1RVVzzMaiA | B501: El Pelicano | C501: Restaurant | D501: Restaurant | E501: =VLOOKUP(D501,Dict!A:B,2,FALSE) -> Hospitality & Tourism | F501: Food, Point Of Interest, Establishment | G501: 3 | H501: 4.2 | I501: 1772 | J501: Calle Duarte Esq, Santo Domingo | K501: 18.447914 | L501: -69.603705
A502: ChIJcS6j_zh-r44RypEyOtgTnYU | B502: The Boat House | C502: Restaurant | D502: Restaurant | E502: =VLOOKUP(D502,Dict!A:B,2,FALSE) -> Hospitality & Tourism | F502: Food, Point Of Interest, Establishment | G502: 2 | H502: 4.3 | I502: 637 | J502: Calle Duarte 34, Boca Chica | K502: 18.447283 | L502: -69.606575
A503: ChIJESEyrTl-r44RXN3oXo5HsTY | B503: MOMO PARADISE | C503: Restaurant | D503: Lodging | E503: =VLOOKUP(D503,Dict!A:B,2,FALSE) -> Hospitality & Tourism | F503: Restaurant, Food, Point Of Interest, Establishment | G503: 2 | H503: 4.4 | I503: 374 | J503: Avenue Juan Bautista Vicini 15, Boca Chica | K503: 18.449652 | L503: -69.609574
A504: ChIJwynKcUd-r44R0HvvApHS2ks | B504: Pluyer Pollos Boca Chica | C504: Restaurant | D504: Restaurant | E504: =VLOOKUP(D504,Dict!A:B,2,FALSE) -> Hospitality & Tourism | F504: Food, Point Of Interest, Establishment | G504: 1 | H504: 4.3 | I504: 361 | J504: frente al Ole, Calle José Francisco Peña Goméz, Boca Chica | K504: 18.452695 | L504: -69.605607
A505: ChIJPxxxxTl-r44REFXL7fe4tXA | B505: La Terraza by Gael | C505: Restaurant | D505: Restaurant | E505: =VLOOKUP(D505,Dict!A:B,2,FALSE) -> Hospitality & Tourism | F505: Food, Point Of Interest, Establishment | G505: 2 | H505: 4.1 | I505: 344 | J505: Dominguez, Boca Chica | K505: 18.44704 | L505: -69.608635
A506: ChIJWSUzDkd-r44Rd1zNSx40w4E | B506: Hotel Hamilton | C506: Restaurant | D506: Restaurant | E506: =VLOOKUP(D506,Dict!A:B,2,FALSE) -> Hospitality & Tourism | F506: Food, Point Of Interest, Establishment | G506: Not available | H506: 4 | I506: 338 | J506: Calle José Francisco Peña Goméz 15, Boca Chica | K506: 18.452149 | L506: -69.60588
A507: ChIJ38ACVTF_r44R8FF8dqdiIBw | B507: Palmares Bar Restaurant | C507: Restaurant | D507: Restaurant | E507: =VLOOKUP(D507,Dict!A:B,2,FALSE) -> Hospitality & Tourism | F507: Point Of Interest, Food, Establishment | G507: 1 | H507: 4.3 | I507: 226 | J507: F92V+35X, Juanico Garcia, Boca Chica | K507: 18.450245 | L507: -69.607012
A508: ChIJW3Mm_Dh-r44R5njK1LELoRo | B508: Caribe Beach | C508: Restaurant | D508: Restaurant | E508: =VLOOKUP(D508,Dict!A:B,2,FALSE) -> Hospitality & Tourism | F508: Point Of Interest, Food, Establishment | G508: 2 | H508: 4.3 | I508: 191 | J508: C9WV+W85, Calle Duarte, Boca Chica | K508: 18.447262 | L508: -69.606636
A509: ChIJbdN3-0Z-r44Rgweioe-2gvM | B509: Pala Pizza | C509: Restaurant | D509: Restaurant | E509: =VLOOKUP(D509,Dict!A:B,2,FALSE) -> Hospitality & Tourism | F509: Point Of Interest, Food, Establishment | G509: 2 | H509: 3.8 | I509: 184 | J509: en Hipermercado Olé, Jose Fco, Calle José Francisco Peña Goméz Esq, Boca Chica | K509: 18.452927 | L509: -69.605803
A510: ChIJMcTn7Th-r44RoWPOmKxlNlU | B510: Ramonita Caché pescados fritos | C510: Restaurant | D510: Restaurant | E510: =VLOOKUP(D510,Dict!A:B,2,FALSE) -> Hospitality & Tourism | F510: Food, Point Of Interest, Establishment | G510: 1 | H510: 4.2 | I510: 158 | J510: C9XV+9PJ, Boca Chica | K510: 18.448466 | L510: -69.60574
A511: ChIJ0cRuJAB_r44RIhna9qaJLlU | B511: Pizzeria Da Fabry - Pizzeria Italiana | C511: Restaurant | D511: Restaurant | E511: =VLOOKUP(D511,Dict!A:B,2,FALSE) -> Hospitality & Tourism | F511: Food, Point Of Interest, Establishment | G511: Not available | H511: 4.6 | I511: 123 | J511: avenida del sur Boca Chica, Santo Domingo Este | K511: 18.450203 | L511: -69.60587
A512: ChIJu9fh-jh-r44R9fyjElR81gA | B512: Benitez Restaurant | C512: Restaurant | D512: Restaurant | E512: =VLOOKUP(D512,Dict!A:B,2,FALSE) -> Hospitality & Tourism | F512: Food, Point Of Interest, Establishment | G512: Not available | H512: 3.6 | I512: 105 | J512: C9XV+3JW, Avenue Duarte, Boca Chica | K512: 18.447739 | L512: -69.605924
A513: ChIJ5WYeojd_r44RUbvm1SBWPME | B513: Bless Brunch & Café | C513: Restaurant | D513: Cafe | E513: =VLOOKUP(D513,Dict!A:B,2,FALSE) -> Hospitality & Tourism | F513: Restaurant, Store, Food, Point Of Interest, Establishment | G513: Not available | H513: 4.9 | I513: 101 | J513: C9XV+RMC, Calle José Francisco Peña Goméz, Boca Chica | K513: 18.449612 | L513: -69.605857
A514: ChIJf5s4-Th-r44RCx5AFqPDbu4 | B514: Helados Bon | C514: Restaurant | D514: Restaurant | E514: =VLOOKUP(D514,Dict!A:B,2,FALSE) -> Hospitality & Tourism | F514: Point Of Interest, Food, Establishment | G514: 1 | H514: 4.2 | I514: 99 | J514: C9XV+2CQ, Boca Chica | K514: 18.447596 | L514: -69.606403
A515: ChIJJe57lHl_r44Rnva_zKraq6Q | B515: Restaurant Ocean Republic | C515: Restaurant | D515: Restaurant | E515: =VLOOKUP(D515,Dict!A:B,2,FALSE) -> Hospitality & Tourism | F515: Point Of Interest, Food, Establishment | G515: Not available | H515: 4.5 | I515: 76 | J515: Av. Duarte 28 Boca Chica, Santo Domingo Este | K515: 18.447603 | L515: -69.606162
A516: ChIJE7W6_zh-r44RjbagAYKpYBw | B516: Boca Breeze | C516: Restaurant | D516: Restaurant | E516: =VLOOKUP(D516,Dict!A:B,2,FALSE) -> Hospitality & Tourism | F516: Point Of Interest, Food, Establishment | G516: 2 | H516: 4.3 | I516: 63 | J516: Avenue Duarte, Boca Chica | K516: 18.447397 | L516: -69.606427
A517: ChIJTy7x8Dh-r44RYTLTGUQ4kfM | B517: Red Shark Beach Bar & Restaurant | C517: Restaurant | D517: Restaurant | E517: =VLOOKUP(D517,Dict!A:B,2,FALSE) -> Hospitality & Tourism | F517: Food, Point Of Interest, Establishment | G517: Not available | H517: 4.6 | I517: 43 | J517: C9XV+6H9, Boca Chica | K517: 18.448047 | L517: -69.606028
A518: ChIJZWJf8Th-r44R8m7LXn7X8Iw | B518: Mar Adentro Gourmet | C518: Restaurant | D518: Restaurant | E518: =VLOOKUP(D518,Dict!A:B,2,FALSE) -> Hospitality & Tourism | F518: Food, Point Of Interest, Establishment | G518: Not available | H518: 4.2 | I518: 32 | J518: C9XV+8H6, Boca Chica | K518: 18.44829 | L518: -69.606111
A519: ChIJVVVVRVt-r44R2yuSZ9cbVGI | B519: BAR MONACO | C519: Restaurant | D519: Restaurant | E519: =VLOOKUP(D519,Dict!A:B,2,FALSE) -> Hospitality & Tourism | F519: Food, Point Of Interest, Establishment | G519: Not available | H519: 3.9 | I519: 25 | J519: F96W+Q73, Boca Chica | K519: 18.461876 | L519: -69.604327
A520: ChIJ1dmi7Td-r44RguwWqbg_Xqs | B520: club tropical de los santos | C520: Restaurant | D520: Lodging | E520: =VLOOKUP(D520,Dict!A:B,2,FALSE) -> Hospitality & Tourism | F520: Restaurant, Food, Point Of Interest, Establishment | G520: Not available | H520: 4.1 | I520: 23 | J520: esquina caracol, Avenue 20 de Diciembre, Boca Chica | K520: 18.449281 | L520: -69.605979
A521: ChIJA4rqZQB_r44RXli-YAwuYj4 | B521: Restaurant bar YGOM & asoc | C521: Restaurant | D521: Restaurant | E521: =VLOOKUP(D521,Dict!A:B,2,FALSE) -> Hospitality & Tourism | F521: Point Of Interest, Food, Establishment | G521: Not available | H521: 2.7 | I521: 22 | J521: C9WV+W7C, Boca Chica | K521: 18.44726 | L521: -69.606801
A522: ChIJ_-cAO0d_r44RXlimCNkD6_w | B522: Batey Restaurant Fusion Cuisine | C522: Restaurant | D522: Restaurant | E522: =VLOOKUP(D522,Dict!A:B,2,FALSE) -> Hospitality & Tourism | F522: Point Of Interest, Food, Establishment | G522: Not available | H522: 3.5 | I522: 21 | J522: Calle Duarte 36, Boca Chica | K522: 18.44767 | L522: -69.606815
A523: ChIJE4eb-T9-r44Rv9xo0qCSi04 | B523: LOS 5 HERMANOS | C523: Restaurant | D523: Restaurant | E523: =VLOOKUP(D523,Dict!A:B,2,FALSE) -> Hospitality & Tourism | F523: Food, Point Of Interest, Establishment | G523: Not available | H523: 4.1 | I523: 14 | J523: CCX2+HP3, Calle Duarte, Boca Chica | K523: 18.448878 | L523: -69.598206
A524: ChIJE4eb-T9-r44RMtMHmdGNWoM | B524: Restaurante Oca Pia | C524: Restaurant | D524: Restaurant | E524: =VLOOKUP(D524,Dict!A:B,2,FALSE) -> Hospitality & Tourism | F524: Food, Point Of Interest, Establishment | G524: Not available | H524: 4.6 | I524: 5 | J524: CCX2+HP3, Calle Duarte, Boca Chica | K524: 18.448878 | L524: -69.598206
A525: ChIJzf8UfWx_r44Rej9r9AALMOs | B525: È tutta n'ata storia... | C525: Restaurant | D525: Restaurant | E525: =VLOOKUP(D525,Dict!A:B,2,FALSE) -> Hospitality & Tourism | F525: Food, Point Of Interest, Establishment | G525: Not available | H525: 5 | I525: 5 | J525: Calle Duarte 39, Boca Chica | K525: 18.449624 | L525: -69.597872
A526: ChIJAwHINz9-r44RByjCSPk9dXA | B526: Oyster Bay | C526: Restaurant | D526: Restaurant | E526: =VLOOKUP(D526,Dict!A:B,2,FALSE) -> Hospitality & Tourism | F526: Food, Point Of Interest, Establishment | G526: Not available | H526: 3.6 | I526: 5 | J526: C9XW+9Q4, Calle Duarte, Boca Chica | K526: 18.44839 | L526: -69.603045
A527: ChIJq2BRhTh-r44Rze70bgEbgq8 | B527: LA TIA ESPERANZA.restaurant and grill. | C527: Restaurant | D527: Restaurant | E527: =VLOOKUP(D527,Dict!A:B,2,FALSE) -> Hospitality & Tourism | F527: Food, Point Of Interest, Establishment | G527: Not available | H527: 4.4 | I527: 5 | J527: C9XV+PJG, Avenue 20 de Diciembre, Boca Chica | K527: 18.4493 | L527: -69.605912
A528: ChIJVfHVtzh-r44RcZTjls_-GO8 | B528: Órale Mexican Restaurant | C528: Restaurant | D528: Restaurant | E528: =VLOOKUP(D528,Dict!A:B,2,FALSE) -> Hospitality & Tourism | F528: Food, Point Of Interest, Establishment | G528: Not available | H528: 3.8 | I528: 4 | J528: C9XW+986, Boca Chica | K528: 18.448405 | L528: -69.604226
... A586: ChIJtWkUWkh-r44RSasuBpBopE4 | B586: La tienda de Fenix | C586: Store | D586: Clothing Store | E586: =VLOOKUP(D586,Dict!A:B,2,FALSE) -> Retail & Shopping | F586: Store, Point Of Interest, Establishment | G586: Not available | H586: 4.2 | I586: 27 | J586: Juan Alberto Ozoria, Boca Chica | K586: 18.451265 | L586: -69.612851
A587: ChIJT9t_JzZ-r44RoZR2PBUPEic | B587: Sabores Ice Cream | C587: Store | D587: Store | E587: =VLOOKUP(D587,Dict!A:B,2,FALSE) -> Retail & Shopping | F587: Food, Point Of Interest, Establishment | G587: 1 | H587: 4.5 | I587: 24 | J587: F92P+8JR, 24 De Junio, Boca Chica | K587: 18.450862 | L587: -69.613484
A588: ChIJafdA60Z-r44R7NoZYWGXI14 | B588: Ferretería Francis SRL | C588: Store | D588: Hardware Store | E588: =VLOOKUP(D588,Dict!A:B,2,FALSE) -> B2B & Logistics | F588: Store, Point Of Interest, Establishment | G588: Not available | H588: 4.7 | I588: 19 | J588: F93V+HRV, Boca Chica | K588: 18.453997 | L588: -69.605468
A589: ChIJc365bzZ-r44RcD3s0uGS83s | B589: Farmacia Bárbara María Los Coquitos | C589: Store | D589: Pharmacy | E589: =VLOOKUP(D589,Dict!A:B,2,FALSE) -> Health & Wellness | F589: Store, Health, Point Of Interest, Establishment | G589: Not available | H589: 4.4 | I589: 17 | J589: Avenue 20 de Diciembre, Boca Chica | K589: 18.449026 | L589: -69.6146
A590: ChIJN5jjekd-r44RfA6HNsJ2yAQ | B590: Farmacia Barbara Maria II | C590: Store | D590: Pharmacy | E590: =VLOOKUP(D590,Dict!A:B,2,FALSE) -> Health & Wellness | F590: Health, Store, Point Of Interest, Establishment | G590: Not available | H590: 4.4 | I590: 16 | J590: Calle José Francisco Peña Goméz, Boca Chica | K590: 18.450568 | L590: -69.605856
A591: ChIJs21C9kZ-r44RBJ7wQcNZDWk | B591: Treasure Divers | C591: Store | D591: Store | E591: =VLOOKUP(D591,Dict!A:B,2,FALSE) -> Retail & Shopping | F591: School, Point Of Interest, Establishment | G591: Not available | H591: 4.6 | I591: 9 | J591: Avenue Duarte 28, Boca Chica | K591: 18.447632 | L591: -69.606275
A592: ChIJ-VH89zh-r44RrEp0MwD5SJs | B592: Selaida Tropical | C592: Store | D592: Store | E592: =VLOOKUP(D592,Dict!A:B,2,FALSE) -> Retail & Shopping | F592: Point Of Interest, Establishment | G592: Not available | H592: 5 | I592: 7 | J592: C9XV+69C, Avenue San Rafael, Boca Chica | K592: 18.448075 | L592: -69.606609
A593: ChIJ93xKUwd_r44Rn8krIWWm060 | B593: El Colmadito de la esquina | C593: Store | D593: Store | E593: =VLOOKUP(D593,Dict!A:B,2,FALSE) -> Retail & Shopping | F593: Point Of Interest, Establishment | G593: Not available | H593: 4.3 | I593: 6 | J593: SantoDomingo | K593: 18.449454 | L593: -69.605899
...
